pyproject.toml
autotuneml/__init__.py
autotuneml/data.py
autotuneml/fai_code.py
autotuneml/fastai_train.py
autotuneml/log_config.py
autotuneml/lstm.py
autotuneml/main.py
autotuneml/skl_train.py
autotuneml/version.py
autotuneml/configs/__init__.py
autotuneml/configs/config_class.py
autotuneml/configs/optimization_config.py
autotuneml/configs/pipeline_config.py
autotuneml-0.4.6.dist-info/METADATA
autotuneml-0.4.6.dist-info/WHEEL
autotuneml-0.4.6.dist-info/RECORD
